apidays24pj/__init__.py
apidays24pj/py.typed
apidays24pj/_jsii/__init__.py
apidays24pj/_jsii/apidays24pj@0.0.15.jsii.tgz
apidays24pj-0.0.15.dist-info/LICENSE
apidays24pj-0.0.15.dist-info/METADATA
apidays24pj-0.0.15.dist-info/WHEEL
apidays24pj-0.0.15.dist-info/top_level.txt
apidays24pj-0.0.15.dist-info/RECORD
